persisto/__init__.py
persisto/client.py
persisto/errors.py
persisto/exception.py
persisto/models.py
persisto-0.1.1.dist-info/METADATA
persisto-0.1.1.dist-info/WHEEL
persisto-0.1.1.dist-info/top_level.txt
persisto-0.1.1.dist-info/RECORD
