Metadata-Version: 2.4
Name: persisto
Version: 0.1.1
Summary: Developer SDK for Persisto: a persistent memory layer for AI apps
Author-email: Trusten <trusten.lehmannkarp@gmail.com>
License: Proprietary
Project-URL: Homepage, https://github.com/trusten5/persisto-smaas-python-sdk
Project-URL: Documentation, https://github.com/trusten5/persisto-smaas-python-sdk#readme
Project-URL: Issues, https://github.com/trusten5/persisto-smaas-python-sdk/issues
Classifier: Development Status :: 3 - Alpha
Classifier: Intended Audience :: Developers
Classifier: License :: Other/Proprietary License
Classifier: Programming Language :: Python :: 3
Classifier: Programming Language :: Python :: 3 :: Only
Classifier: Programming Language :: Python :: 3.9
Classifier: Programming Language :: Python :: 3.10
Classifier: Programming Language :: Python :: 3.11
Classifier: Programming Language :: Python :: 3.12
Classifier: Topic :: Software Development :: Libraries
Requires-Python: >=3.9
Requires-Dist: requests>=2.31
Requires-Dist: pydantic>=2.5
Requires-Dist: tenacity>=8.2
